{
  "aviaSport" : "Авиационный спорт",
  "autoSport" : "Автомобильный спорт",
  "aquaAerobics" : "Аквааэробика",
  "alpinism" : "Альпинизм",
  "armrestling" : "Армрестлинг",
  "aerobics" : "Аэробика",
  "badminton" : "Бадминтон",
  "basketball" : "Баскетбол",
  "run" : "Бег",
  "basejumping" : "Бейсджампинг",
  "biathlon" : "Биатлон",
  "bobsled" : "Бобслей",
  "boxing" : "Бокс",
  "bowling" : "Боулинг",
  "wakeboard" : "Вейкборд",
  "cycling" : "Велосипедный спорт",
  "1" : "Виндсерфинг",
  "2" : "Водное поло",
  "3" : "Воднолыжный спорт",
  "4" : "Волейбол",
  "5" : "Гандбол",
  "6" : "Гимнастика",
  "7" : "Гольф",
  "8" : "Горный трекинг",
  "9" : "Гребной спорт",
  "10" : "Дельтапланеризм",
  "11" : "Единоборства и борьба",
  "12" : "Кайтинг",
  "13" : "Капоэйра",
  "14" : "Картинг",
  "15" : "Керлинг",
  "16" : "Конный спорт",
  "17" : "Конькобежный спорт",
  "18" : "Крикет",
  "19" : "Легкая атлетика",
  "20" : "Маутинбайк",
  "21" : "Мотоспорт",
  "22" : "Охота",
  "23" : "Парапланеризм",
  "24" : "Парашютный спорт",
  "25" : "Парусный спорт",
  "26" : "Пейнтбол",
  "27" : "Плавание",
  "28" : "Пляжный волейбол/футбол/гандбол",
  "29" : "Прыжки в воду",
  "30" : "Прыжки на батуте",
  "31" : "Рафтинг",
  "32" : "Регби",
  "33" : "Ролики",
  "34" : "Роупджампинг",
  "35" : "Рыбалка",
  "36" : "Санный спорт",
  "37" : "Синхронное плавание",
  "38" : "Скалолазание",
  "39" : "Сквош",
  "40" : "Скейтбординг",
  "41" : "Сноукайтинг",
  "42" : "Софтбол",
  "43" : "Спелеология",
  "44" : "Спортивная ходьба",
  "45" : "Спортивные и бальные танцы",
  "46" : "Стрелковый спорт",
  "47" : "Теннис",
  "48" : "Трекинг",
  "49" : "Тяжелая атлетика",
  "50" : "Управление гидроциклом",
  "51" : "Управление квадроциклом",
  "52" : "Управление снегоходом",
  "53" : "Фехтование",
  "54" : "Фигурное катание",
  "55" : "Фристайл (лыжный фристайл)",
  "56" : "Футбол",
  "57" : "Хелиски",
  "58" : "Хоккей",
  "59" : "Яхтинг"
}